PIPELINED MIPS/mips_pipeline.sv
module top(input  logic clk, reset, 
           output logic [31:0] writedata, dataadr, 
           output logic memwrite);

  logic [31:0] pc, instr, readdata;

  mips mips(clk, reset, pc, instr, memwrite, dataadr, writedata, readdata);
  imem imem(pc[7:2], instr);
  dmem dmem(clk, memwrite, dataadr, writedata, readdata);
endmodule

module mips(input  logic clk, reset,
            output logic [31:0] pc,
            input  logic [31:0] instr,
            output logic memwrite,
            output logic [31:0] aluout, writedata,
            input  logic [31:0] readdata);

  logic [2:0] alucontrol_d;
  logic memtoreg_d, memwrite_d, pcsrc_d, alusrc_d, regdst_d, regwrite_d, jump_d, branch_d;
  logic [31:0] instr_d;

  controller c(instr_d[31:26], instr_d[5:0], 
               memtoreg_d, memwrite_d, alusrc_d, 
               regdst_d, regwrite_d, jump_d, branch_d, alucontrol_d);

  datapath dp(clk, reset, memtoreg_d, memwrite_d, pcsrc_d, alusrc_d, 
              regdst_d, regwrite_d, jump_d, branch_d, alucontrol_d,
              pc, instr, memwrite, aluout, writedata, readdata, instr_d);
endmodule

module controller(input  logic [5:0] op, funct,
                  output logic memtoreg, memwrite, alusrc,
                  output logic regdst, regwrite, jump, branch,
                  output logic [2:0] alucontrol);

  logic [1:0] aluop;
  maindec md(op, memtoreg, memwrite, branch, alusrc, regdst, regwrite, jump, aluop);
  aludec  ad(funct, aluop, alucontrol);
endmodule

module maindec(input  logic [5:0] op,
               output logic memtoreg, memwrite, branch, alusrc,
               output logic regdst, regwrite, jump,
               output logic [1:0] aluop);

  logic [8:0] controls;
  assign {regwrite, regdst, alusrc, branch, memwrite, memtoreg, jump, aluop} = controls;

  always_comb
    case(op)
      6'b000000: controls = 9'b1100000_10; 
      6'b100011: controls = 9'b1010010_00; 
      6'b101011: controls = 9'b0010100_00; 
      6'b000100: controls = 9'b0001000_01; 
      6'b001000: controls = 9'b1010000_00; 
      6'b000010: controls = 9'b0000001_00; 
      default:   controls = 9'b0000000_00;
    endcase
endmodule

module aludec(input  logic [5:0] funct,
              input  logic [1:0] aluop,
              output logic [2:0] alucontrol);

  always_comb
    case(aluop)
      2'b00: alucontrol = 3'b010; 
      2'b01: alucontrol = 3'b110; 
      default: case(funct)          
          6'b100000: alucontrol = 3'b010; 
          6'b100010: alucontrol = 3'b110; 
          6'b100100: alucontrol = 3'b000; 
          6'b100101: alucontrol = 3'b001; 
          6'b101010: alucontrol = 3'b111; 
          default:   alucontrol = 3'bxxx; 
        endcase
    endcase
endmodule

module datapath(input  logic clk, reset,
                input  logic memtoreg_d, memwrite_d, 
                output logic pcsrc_d,
                input  logic alusrc_d, regdst_d, regwrite_d, 
                input  logic jump_d, branch_d,
                input  logic [2:0] alucontrol_d,
                output logic [31:0] pc_f,
                input  logic [31:0] instr_f,
                output logic memwrite_m,
                output logic [31:0] aluout_m, writedata_m,
                input  logic [31:0] readdata_m,
                output logic [31:0] instr_d);

  logic [31:0] pcnext_f, pcplus4_f, pcplus4_d, pcbranch_d;
  logic [31:0] rd1_d, rd2_d, rd1_d_final, rd2_d_final;
  logic [31:0] signimm_d, signimmsh_d, srca_e, srcb_e, writedata_e;
  logic [31:0] aluout_e, aluout_w, readdata_w, result_w, signimm_e;
  logic [4:0]  rs_e, rt_e, rd_e, writereg_e, writereg_m, writereg_w;
  logic [2:0]  alucontrol_e;
  logic        alusrc_e, regdst_e, regwrite_e, memtoreg_e, memwrite_e;
  logic        regwrite_m, memtoreg_m, regwrite_w, memtoreg_w;
  logic [1:0]  forwarda_e, forwardb_e;
  logic        stall_f, stall_d, flush_e;
  logic [31:0] srca_e_final, writedata_e_final;

  hazard h(instr_d[25:21], instr_d[20:16], rs_e, rt_e, writereg_e, writereg_m, writereg_w,
           regwrite_e, regwrite_m, regwrite_w, memtoreg_e, memtoreg_m, branch_d, pcsrc_d,
           forwarda_e, forwardb_e, stall_f, stall_d, flush_e);

  assign pcsrc_d = branch_d & (rd1_d_final == rd2_d_final);

  floprc #(32) pcreg(clk, reset, 1'b0, ~stall_f, pcnext_f, pc_f);
  adder         pcadd1(pc_f, 32'b100, pcplus4_f);
  mux2 #(32)    pcbrmux(pcplus4_f, pcbranch_d, pcsrc_d, pcnext_f);

  floprc #(32) f_d_instr(clk, reset, pcsrc_d, ~stall_d, instr_f, instr_d);
  floprc #(32) f_d_pc(clk, reset, pcsrc_d, ~stall_d, pcplus4_f, pcplus4_d);

  regfile rf(clk, regwrite_w, instr_d[25:21], instr_d[20:16], writereg_w, result_w, rd1_d, rd2_d);
  signext se(instr_d[15:0], signimm_d);
  sl2     immsh(signimm_d, signimmsh_d);
  adder   pcadd2(pcplus4_d, signimmsh_d, pcbranch_d);

  assign rd1_d_final = (instr_d[25:21] != 0) ? ((instr_d[25:21] == writereg_m && regwrite_m) ? aluout_m : rd1_d) : 0;
  assign rd2_d_final = (instr_d[20:16] != 0) ? ((instr_d[20:16] == writereg_m && regwrite_m) ? aluout_m : rd2_d) : 0;

  always_ff @(posedge clk, posedge reset)
    if (reset || flush_e) begin
      regwrite_e <= 0; memtoreg_e <= 0; memwrite_e <= 0;
      alucontrol_e <= 0; alusrc_e <= 0; regdst_e <= 0;
      srca_e <= 0; writedata_e <= 0; rs_e <= 0; rt_e <= 0; rd_e <= 0; signimm_e <= 0;
    end else begin
      regwrite_e <= regwrite_d; memtoreg_e <= memtoreg_d; memwrite_e <= memwrite_d;
      alucontrol_e <= alucontrol_d; alusrc_e <= alusrc_d; regdst_e <= regdst_d;
      srca_e <= rd1_d; writedata_e <= rd2_d; rs_e <= instr_d[25:21]; 
      rt_e <= instr_d[20:16]; rd_e <= instr_d[15:11]; signimm_e <= signimm_d;
    end

  mux3 #(32) faemux(srca_e, result_w, aluout_m, forwarda_e, srca_e_final);
  mux3 #(32) fbemux(writedata_e, result_w, aluout_m, forwardb_e, writedata_e_final);
  
  mux2 #(32) srcbmux(writedata_e_final, signimm_e, alusrc_e, srcb_e);
  alu        alu(srca_e_final, srcb_e, alucontrol_e, aluout_e, zero_e);
  mux2 #(5)  wrmux(rt_e, rd_e, regdst_e, writereg_e);
  logic zero_e;

  always_ff @(posedge clk, posedge reset)
    if (reset) begin
      regwrite_m <= 0; memtoreg_m <= 0; memwrite_m <= 0;
      aluout_m <= 0; writedata_m <= 0; writereg_m <= 0;
    end else begin
      regwrite_m <= regwrite_e; memtoreg_m <= memtoreg_e; memwrite_m <= memwrite_e;
      aluout_m <= aluout_e; writedata_m <= writedata_e_final; writereg_m <= writereg_e;
    end

  always_ff @(posedge clk, posedge reset)
    if (reset) begin
      regwrite_w <= 0; memtoreg_w <= 0; readdata_w <= 0; aluout_w <= 0; writereg_w <= 0;
    end else begin
      regwrite_w <= regwrite_m; memtoreg_w <= memtoreg_m;
      readdata_w <= readdata_m; aluout_w <= aluout_m; writereg_w <= writereg_m;
    end

  mux2 #(32) resmux(aluout_w, readdata_w, memtoreg_w, result_w);
endmodule

module hazard(input  logic [4:0] rs_d, rt_d, rs_e, rt_e, writereg_e, writereg_m, writereg_w,
              input  logic regwrite_e, regwrite_m, regwrite_w, memtoreg_e, memtoreg_m, 
              input  logic branch_d, pcsrc_d,
              output logic [1:0] forwarda_e, forwardb_e,
              output logic stall_f, stall_d, flush_e);

  logic lwstall, branchstall;

  always_comb begin
    forwarda_e = 2'b00; forwardb_e = 2'b00;
    if (rs_e != 0)
      if (rs_e == writereg_m && regwrite_m)      forwarda_e = 2'b10;
      else if (rs_e == writereg_w && regwrite_w) forwarda_e = 2'b01;
    if (rt_e != 0)
      if (rt_e == writereg_m && regwrite_m)      forwardb_e = 2'b10;
      else if (rt_e == writereg_w && regwrite_w) forwardb_e = 2'b01;
  end

  assign lwstall = ((rs_d == rt_e) || (rt_d == rt_e)) && memtoreg_e;
  
  assign branchstall = branch_d & 
                       (regwrite_e & (writereg_e == rs_d | writereg_e == rt_d) |
                        memtoreg_m & (writereg_m == rs_d | writereg_m == rt_d));

  assign stall_f = lwstall | branchstall;
  assign stall_d = lwstall | branchstall;
  assign flush_e = lwstall | branchstall | pcsrc_d;
endmodule

module regfile(input  logic clk, we3, input  logic [4:0] ra1, ra2, wa3,
               input  logic [31:0] wd3, output logic [31:0] rd1, rd2);
  logic [31:0] rf[31:0];
  always_ff @(negedge clk) if (we3) rf[wa3] <= wd3;
  assign rd1 = (ra1 != 0) ? rf[ra1] : 0;
  assign rd2 = (ra2 != 0) ? rf[ra2] : 0;
endmodule

module alu(input  logic [31:0] a, b, input  logic [2:0] alucontrol,
           output logic [31:0] result, output logic zero);
  always_comb
    case(alucontrol)
      3'b010: result = a + b;
      3'b110: result = a - b;
      3'b000: result = a & b;
      3'b001: result = a | b;
      3'b111: result = a < b ? 32'd1 : 32'd0;
      default: result = 32'bx;
    endcase
  assign zero = (result == 32'b0);
endmodule

module dmem(input  logic clk, we, input  logic [31:0] a, wd, output logic [31:0] rd);
  logic [31:0] RAM[63:0];
  assign rd = RAM[a[31:2]];
  always_ff @(posedge clk) if (we) RAM[a[31:2]] <= wd;
endmodule

module imem(input  logic [5:0] a, output logic [31:0] rd);
  logic [31:0] RAM[63:0];
  initial $readmemh("mips_pipeline_memfile.dat", RAM);
  assign rd = RAM[a];
endmodule

module adder(input  logic [31:0] a, b, output logic [31:0] y);
  assign y = a + b;
endmodule

module sl2(input  logic [31:0] a, output logic [31:0] y);
  assign y = {a[29:0], 2'b00};
endmodule

module signext(input  logic [15:0] a, output logic [31:0] y);
  assign y = {{16{a[15]}}, a};
endmodule

module floprc #(parameter WIDTH = 8)
                (input  logic clk, reset, clear, en, input  logic [WIDTH-1:0] d, output logic [WIDTH-1:0] q);
  always_ff @(posedge clk, posedge reset)
    if (reset)      q <= 0;
    else if (clear) q <= 0;
    else if (en)    q <= d;
endmodule

module mux2 #(parameter WIDTH = 8)
             (input  logic [WIDTH-1:0] d0, d1, input  logic s, output logic [WIDTH-1:0] y);
  assign y = s ? d1 : d0;
endmodule

module mux3 #(parameter WIDTH = 8)
             (input  logic [WIDTH-1:0] d0, d1, d2, input  logic [1:0] s, output logic [WIDTH-1:0] y);
  assign y = (s == 2'b10) ? d2 : (s == 2'b01 ? d1 : d0);
endmodule

PIPELINED MIPS/mips_pipeline_tb.sv
module tb;
  logic clk;
  logic reset;
  logic [31:0] writedata, dataadr;
  logic memwrite;

  top dut(clk, reset, writedata, dataadr, memwrite);

  initial begin
    clk = 0;
    forever #5 clk = ~clk;
  end

  initial begin
    $dumpfile("dump.vcd");
    $dumpvars(0, tb);
    reset = 1;
    #12 reset = 0;
  end

  always @(negedge clk) begin
    if (memwrite) begin
      if (dataadr === 84 && writedata === 7) begin
        $display("Simulation Succeeded: Value 7 written to Address 84.");
        $finish; 
      end 
      else if (dataadr === 80) begin
      end
      else begin
        $display("Simulation Failed: Unexpected write!");
        $display("Address: %d (Hex: %h), Data: %d (Hex: %h)", dataadr, dataadr, writedata, writedata);
        $finish;
      end
    end
  end

  initial begin
    #1000; 
    $display("Simulation Timed Out.");
    $finish;
  end
endmodule

PIPELINED MIPS/dump.vcd
$date
	Mon May 04 19:28:07 2026
$end
$version
	Icarus Verilog
$end
$timescale
	1s
$end
$scope module tb $end
$var wire 32 ! writedata [31:0] $end
$var wire 1 " memwrite $end
$var wire 32 # dataadr [31:0] $end
$var reg 1 $ clk $end
$var reg 1 % reset $end
$scope module dut $end
$var wire 1 $ clk $end
$var wire 1 % reset $end
$var wire 32 & writedata [31:0] $end
$var wire 32 ' readdata [31:0] $end
$var wire 32 ( pc [31:0] $end
$var wire 1 " memwrite $end
$var wire 32 ) instr [31:0] $end
$var wire 32 * dataadr [31:0] $end
$scope module dmem $end
$var wire 1 $ clk $end
$var wire 32 + rd [31:0] $end
$var wire 1 " we $end
$var wire 32 , wd [31:0] $end
$var wire 32 - a [31:0] $end
$upscope $end
$scope module imem $end
$var wire 6 . a [5:0] $end
$var wire 32 / rd [31:0] $end
$upscope $end
$scope module mips $end
$var wire 1 $ clk $end
$var wire 32 0 instr [31:0] $end
$var wire 32 1 readdata [31:0] $end
$var wire 1 % reset $end
$var wire 32 2 writedata [31:0] $end
$var wire 1 3 regwrite_d $end
$var wire 1 4 regdst_d $end
$var wire 1 5 pcsrc_d $end
$var wire 32 6 pc [31:0] $end
$var wire 1 7 memwrite_d $end
$var wire 1 " memwrite $end
$var wire 1 8 memtoreg_d $end
$var wire 1 9 jump_d $end
$var wire 32 : instr_d [31:0] $end
$var wire 1 ; branch_d $end
$var wire 1 < alusrc_d $end
$var wire 32 = aluout [31:0] $end
$var wire 3 > alucontrol_d [2:0] $end
$scope module c $end
$var wire 6 ? funct [5:0] $end
$var wire 6 @ op [5:0] $end
$var wire 1 3 regwrite $end
$var wire 1 4 regdst $end
$var wire 1 7 memwrite $end
$var wire 1 8 memtoreg $end
$var wire 1 9 jump $end
$var wire 1 ; branch $end
$var wire 1 < alusrc $end
$var wire 2 A aluop [1:0] $end
$var wire 3 B alucontrol [2:0] $end
$scope module ad $end
$var wire 6 C funct [5:0] $end
$var wire 2 D aluop [1:0] $end
$var reg 3 E alucontrol [2:0] $end
$upscope $end
$scope module md $end
$var wire 6 F op [5:0] $end
$var wire 1 3 regwrite $end
$var wire 1 4 regdst $end
$var wire 1 7 memwrite $end
$var wire 1 8 memtoreg $end
$var wire 1 9 jump $end
$var wire 1 ; branch $end
$var wire 1 < alusrc $end
$var wire 2 G aluop [1:0] $end
$var reg 9 H controls [8:0] $end
$upscope $end
$upscope $end
$scope module dp $end
$var wire 3 I alucontrol_d [2:0] $end
$var wire 1 < alusrc_d $end
$var wire 1 ; branch_d $end
$var wire 1 $ clk $end
$var wire 32 J instr_f [31:0] $end
$var wire 1 9 jump_d $end
$var wire 1 8 memtoreg_d $end
$var wire 1 7 memwrite_d $end
$var wire 1 5 pcsrc_d $end
$var wire 32 K readdata_m [31:0] $end
$var wire 1 4 regdst_d $end
$var wire 1 3 regwrite_d $end
$var wire 1 % reset $end
$var wire 1 L zero_e $end
$var wire 5 M writereg_e [4:0] $end
$var wire 32 N writedata_e_final [31:0] $end
$var wire 1 O stall_f $end
$var wire 1 P stall_d $end
$var wire 32 Q srcb_e [31:0] $end
$var wire 32 R srca_e_final [31:0] $end
$var wire 32 S signimmsh_d [31:0] $end
$var wire 32 T signimm_d [31:0] $end
$var wire 32 U result_w [31:0] $end
$var wire 32 V rd2_d_final [31:0] $end
$var wire 32 W rd2_d [31:0] $end
$var wire 32 X rd1_d_final [31:0] $end
$var wire 32 Y rd1_d [31:0] $end
$var wire 32 Z pcplus4_f [31:0] $end
$var wire 32 [ pcplus4_d [31:0] $end
$var wire 32 \ pcnext_f [31:0] $end
$var wire 32 ] pcbranch_d [31:0] $end
$var wire 32 ^ pc_f [31:0] $end
$var wire 32 _ instr_d [31:0] $end
$var wire 2 ` forwardb_e [1:0] $end
$var wire 2 a forwarda_e [1:0] $end
$var wire 1 b flush_e $end
$var wire 32 c aluout_e [31:0] $end
$var reg 3 d alucontrol_e [2:0] $end
$var reg 32 e aluout_m [31:0] $end
$var reg 32 f aluout_w [31:0] $end
$var reg 1 g alusrc_e $end
$var reg 1 h memtoreg_e $end
$var reg 1 i memtoreg_m $end
$var reg 1 j memtoreg_w $end
$var reg 1 k memwrite_e $end
$var reg 1 " memwrite_m $end
$var reg 5 l rd_e [4:0] $end
$var reg 32 m readdata_w [31:0] $end
$var reg 1 n regdst_e $end
$var reg 1 o regwrite_e $end
$var reg 1 p regwrite_m $end
$var reg 1 q regwrite_w $end
$var reg 5 r rs_e [4:0] $end
$var reg 5 s rt_e [4:0] $end
$var reg 32 t signimm_e [31:0] $end
$var reg 32 u srca_e [31:0] $end
$var reg 32 v writedata_e [31:0] $end
$var reg 32 w writedata_m [31:0] $end
$var reg 5 x writereg_m [4:0] $end
$var reg 5 y writereg_w [4:0] $end
$scope module alu $end
$var wire 3 z alucontrol [2:0] $end
$var wire 1 L zero $end
$var wire 32 { b [31:0] $end
$var wire 32 | a [31:0] $end
$var reg 32 } result [31:0] $end
$upscope $end
$scope module f_d_instr $end
$var wire 1 5 clear $end
$var wire 1 $ clk $end
$var wire 32 ~ d [31:0] $end
$var wire 1 !" en $end
$var wire 1 % reset $end
$var parameter 32 "" WIDTH $end
$var reg 32 #" q [31:0] $end
$upscope $end
$scope module f_d_pc $end
$var wire 1 5 clear $end
$var wire 1 $ clk $end
$var wire 1 $" en $end
$var wire 1 % reset $end
$var wire 32 %" d [31:0] $end
$var parameter 32 &" WIDTH $end
$var reg 32 '" q [31:0] $end
$upscope $end
$scope module faemux $end
$var wire 32 (" d0 [31:0] $end
$var wire 32 )" d2 [31:0] $end
$var wire 32 *" y [31:0] $end
$var wire 2 +" s [1:0] $end
$var wire 32 ," d1 [31:0] $end
$var parameter 32 -" WIDTH $end
$upscope $end
$scope module fbemux $end
$var wire 32 ." d0 [31:0] $end
$var wire 32 /" d2 [31:0] $end
$var wire 32 0" y [31:0] $end
$var wire 2 1" s [1:0] $end
$var wire 32 2" d1 [31:0] $end
$var parameter 32 3" WIDTH $end
$upscope $end
$scope module h $end
$var wire 1 ; branch_d $end
$var wire 1 4" branchstall $end
$var wire 1 b flush_e $end
$var wire 1 5" lwstall $end
$var wire 1 h memtoreg_e $end
$var wire 1 i memtoreg_m $end
$var wire 1 5 pcsrc_d $end
$var wire 1 o regwrite_e $end
$var wire 1 p regwrite_m $end
$var wire 1 q regwrite_w $end
$var wire 5 6" rs_d [4:0] $end
$var wire 5 7" rs_e [4:0] $end
$var wire 5 8" rt_d [4:0] $end
$var wire 5 9" rt_e [4:0] $end
$var wire 1 P stall_d $end
$var wire 1 O stall_f $end
$var wire 5 :" writereg_m [4:0] $end
$var wire 5 ;" writereg_w [4:0] $end
$var wire 5 <" writereg_e [4:0] $end
$var reg 2 =" forwarda_e [1:0] $end
$var reg 2 >" forwardb_e [1:0] $end
$upscope $end
$scope module immsh $end
$var wire 32 ?" y [31:0] $end
$var wire 32 @" a [31:0] $end
$upscope $end
$scope module pcadd1 $end
$var wire 32 A" b [31:0] $end
$var wire 32 B" y [31:0] $end
$var wire 32 C" a [31:0] $end
$upscope $end
$scope module pcadd2 $end
$var wire 32 D" a [31:0] $end
$var wire 32 E" b [31:0] $end
$var wire 32 F" y [31:0] $end
$upscope $end
$scope module pcbrmux $end
$var wire 32 G" d0 [31:0] $end
$var wire 32 H" d1 [31:0] $end
$var wire 1 5 s $end
$var wire 32 I" y [31:0] $end
$var parameter 32 J" WIDTH $end
$upscope $end
$scope module pcreg $end
$var wire 1 K" clear $end
$var wire 1 $ clk $end
$var wire 32 L" d [31:0] $end
$var wire 1 M" en $end
$var wire 1 % reset $end
$var parameter 32 N" WIDTH $end
$var reg 32 O" q [31:0] $end
$upscope $end
$scope module resmux $end
$var wire 32 P" d0 [31:0] $end
$var wire 32 Q" d1 [31:0] $end
$var wire 1 j s $end
$var wire 32 R" y [31:0] $end
$var parameter 32 S" WIDTH $end
$upscope $end
$scope module rf $end
$var wire 1 $ clk $end
$var wire 5 T" ra1 [4:0] $end
$var wire 5 U" ra2 [4:0] $end
$var wire 5 V" wa3 [4:0] $end
$var wire 32 W" wd3 [31:0] $end
$var wire 1 q we3 $end
$var wire 32 X" rd2 [31:0] $end
$var wire 32 Y" rd1 [31:0] $end
$upscope $end
$scope module se $end
$var wire 16 Z" a [15:0] $end
$var wire 32 [" y [31:0] $end
$upscope $end
$scope module srcbmux $end
$var wire 32 \" d0 [31:0] $end
$var wire 32 ]" d1 [31:0] $end
$var wire 1 g s $end
$var wire 32 ^" y [31:0] $end
$var parameter 32 _" WIDTH $end
$upscope $end
$scope module wrmux $end
$var wire 5 `" d0 [4:0] $end
$var wire 5 a" d1 [4:0] $end
$var wire 1 n s $end
$var wire 5 b" y [4:0] $end
$var parameter 32 c" WIDTH $end
$upscope $end
$upscope $end
$upscope $end
$upscope $end
$upscope $end
$enddefinitions $end
$comment Show the parameter values. $end
$dumpall
b101 c"
b100000 _"
b100000 S"
b100000 N"
b100000 J"
b100000 3"
b100000 -"
b100000 &"
b100000 ""
$end
#0
$dumpvars
b0 b"
b0 a"
b0 `"
b0 ^"
b0 ]"
b0 \"
b0 ["
b0 Z"
b0 Y"
b0 X"
b0 W"
b0 V"
b0 U"
b0 T"
b0 R"
b0 Q"
b0 P"
b0 O"
1M"
b100 L"
0K"
b100 I"
b0 H"
b100 G"
b0 F"
b0 E"
b0 D"
b0 C"
b100 B"
b100 A"
b0 @"
b0 ?"
b0 >"
b0 ="
b0 <"
b0 ;"
b0 :"
b0 9"
b0 8"
b0 7"
b0 6"
05"
04"
b0 2"
b0 1"
b0 0"
b0 /"
b0 ."
b0 ,"
b0 +"
b0 *"
b0 )"
b0 ("
b0 '"
b100 %"
1$"
b0 #"
1!"
b100000000000100000000000000101 ~
b0 }
b0 |
b0 {
b0 z
b0 y
b0 x
b0 w
b0 v
b0 u
b0 t
b0 s
b0 r
0q
0p
0o
0n
b0 m
b0 l
0k
0j
0i
0h
0g
b0 f
b0 e
b0 d
b0 c
0b
b0 a
b0 `
b0 _
b0 ^
b0 ]
b100 \
b0 [
b100 Z
b0 Y
b0 X
b0 W
b0 V
b0 U
b0 T
b0 S
b0 R
b0 Q
0P
0O
b0 N
b0 M
1L
bx K
b100000000000100000000000000101 J
bx I
b110000010 H
b10 G
b0 F
bx E
b10 D
b0 C
bx B
b10 A
b0 @
b0 ?
bx >
b0 =
0<
0;
b0 :
09
08
07
b0 6
05
14
13
b0 2
bx 1
b100000000000100000000000000101 0
b100000000000100000000000000101 /
b0 .
b0 -
b0 ,
bx +
b0 *
b100000000000100000000000000101 )
b0 (
bx '
b0 &
1%
0$
b0 #
0"
b0 !
$end
#5
1$
#10
0$
#12
0%
#15
bx V
b10 >
b10 B
b10 E
b10 I
04
1<
b0 A
b0 D
b0 G
b10100 S
b10100 ?"
b10100 E"
bx W
bx X"
b101000000 H
b1000 \
b1000 I"
b1000 L"
b100000000000110000000000001100 )
b100000000000110000000000001100 /
b100000000000110000000000001100 0
b100000000000110000000000001100 J
b100000000000110000000000001100 ~
b1 .
b101 T
b101 @"
b101 ["
b101 Z"
b10 U"
b10 8"
b101 ?
b101 C
b1000 @
b1000 F
xL
bx c
bx }
b1000 Z
b1000 %"
b1000 B"
b1000 G"
b100 (
b100 6
b100 ^
b100 C"
b100 O"
b100000000000100000000000000101 :
b100000000000100000000000000101 _
b100000000000100000000000000101 #"
b11000 ]
b11000 F"
b11000 H"
b100 [
b100 '"
b100 D"
1n
bx d
bx z
1o
bx m
bx Q"
1$
#20
0$
#25
bx N
bx 0"
bx \"
b110000 S
b110000 ?"
b110000 E"
b10 M
b10 <"
b10 b"
b101 Q
b101 {
b101 ^"
0L
b101 c
b101 }
b1100 T
b1100 @"
b1100 ["
b1100 Z"
b11 U"
b11 8"
b1100 ?
b1100 C
b1100 \
b1100 I"
b1100 L"
b100000011001111111111111110111 )
b100000011001111111111111110111 /
b100000011001111111111111110111 0
b100000011001111111111111110111 J
b100000011001111111111111110111 ~
b10 .
bx #
bx *
bx -
bx =
bx e
bx )"
bx /"
1p
b101 t
b101 ]"
b10 s
b10 9"
b10 `"
bx v
bx ."
0n
1g
b10 d
b10 z
b111000 ]
b111000 F"
b111000 H"
b1000 [
b1000 '"
b1000 D"
b100000000000110000000000001100 :
b100000000000110000000000001100 _
b100000000000110000000000001100 #"
b1100 Z
b1100 %"
b1100 B"
b1100 G"
b1000 (
b1000 6
b1000 ^
b1000 C"
b1000 O"
1$
#30
0$
#35
bx X
b11111111111111111111111111011100 S
b11111111111111111111111111011100 ?"
b11111111111111111111111111011100 E"
bx Y
bx Y"
b1100 c
b1100 }
b10000 \
b10000 I"
b10000 L"
b111000100010000000100101 )
b111000100010000000100101 /
b111000100010000000100101 0
b111000100010000000100101 J
b111000100010000000100101 ~
b11 .
b11111111111111111111111111110111 T
b11111111111111111111111111110111 @"
b11111111111111111111111111110111 ["
b1111111111110111 Z"
b111 U"
b11 T"
b111 8"
b11 6"
b110111 ?
b110111 C
b1100 Q
b1100 {
b1100 ^"
b11 M
b11 <"
b11 b"
bx U
bx ,"
bx 2"
bx R"
bx W"
b10000 Z
b10000 %"
b10000 B"
b10000 G"
b1100 (
b1100 6
b1100 ^
b1100 C"
b1100 O"
b100000011001111111111111110111 :
b100000011001111111111111110111 _
b100000011001111111111111110111 #"
b11111111111111111111111111101000 ]
b11111111111111111111111111101000 F"
b11111111111111111111111111101000 H"
b1100 [
b1100 '"
b1100 D"
b1100 t
b1100 ]"
b11 s
b11 9"
b11 `"
b10 x
b10 :"
bx !
bx &
bx ,
bx 2
bx w
b101 #
b101 *
b101 -
b101 =
b101 e
b101 )"
b101 /"
bx f
bx P"
1q
1$
#40
0$
#45
b1 >
b1 B
b1 E
b1 I
14
0<
b10 A
b10 D
b10 G
b11 c
b11 }
b1100 R
b1100 |
b1100 *"
b1000000010010100 S
b1000000010010100 ?"
b1000000010010100 E"
b110000010 H
b101 U
b101 ,"
b101 2"
b101 R"
b101 W"
b11111111111111111111111111110111 Q
b11111111111111111111111111110111 {
b11111111111111111111111111110111 ^"
b111 M
b111 <"
b111 b"
b10 a
b10 +"
b10 ="
b10000000100101 T
b10000000100101 @"
b10000000100101 ["
b10000000100101 Z"
b10 U"
b111 T"
b10 8"
b111 6"
b100101 ?
b100101 C
b0 @
b0 F
b10100 \
b10100 I"
b10100 L"
b11001000011000000101010 )
b11001000011000000101010 /
b11001000011000000101010 0
b11001000011000000101010 J
b11001000011000000101010 ~
b100 .
b10 y
b10 ;"
b10 V"
b101 f
b101 P"
b11 x
b11 :"
b1100 #
b1100 *
b1100 -
b1100 =
b1100 e
b1100 )"
b1100 /"
b11111111111111111111111111110111 t
b11111111111111111111111111110111 ]"
b11111 l
b11111 a"
b111 s
b111 9"
b111 `"
b11 r
b11 7"
bx u
bx ("
b1000000010100100 ]
b1000000010100100 F"
b1000000010100100 H"
b10000 [
b10000 '"
b10000 D"
b111000100010000000100101 :
b111000100010000000100101 _
b111000100010000000100101 #"
b10100 Z
b10100 %"
b10100 B"
b10100 G"
b10000 (
b10000 6
b10000 ^
b10000 C"
b10000 O"
1$
#50
b101 V
b101 W
b101 X"
0$
#55
bx V
bx X
b1100000010101000 S
b1100000010101000 ?"
b1100000010101000 E"
bx W
bx X"
b111 >
b111 B
b111 E
b111 I
b101 N
b101 0"
b101 \"
b11000 \
b11000 I"
b11000 L"
b10000110000000000000000000001 )
b10000110000000000000000000001 /
b10000110000000000000000000001 0
b10000110000000000000000000001 J
b10000110000000000000000000001 ~
b101 .
b11000000101010 T
b11000000101010 @"
b11000000101010 ["
b11000000101010 Z"
b100 U"
b11 T"
b100 8"
b11 6"
b101010 ?
b101010 C
b100 M
b100 <"
b100 b"
b101 Q
b101 {
b101 ^"
b111 c
b111 }
b11 R
b11 |
b11 *"
b10 a
b10 +"
b10 ="
b1100 U
b1100 ,"
b1100 2"
b1100 R"
b1100 W"
b11000 Z
b11000 %"
b11000 B"
b11000 G"
b10100 (
b10100 6
b10100 ^
b10100 C"
b10100 O"
b11001000011000000101010 :
b11001000011000000101010 _
b11001000011000000101010 #"
b1100000010111100 ]
b1100000010111100 F"
b1100000010111100 H"
b10100 [
b10100 '"
b10100 D"
b10000000100101 t
b10000000100101 ]"
b100 l
b100 a"
b10 s
b10 9"
b10 `"
b111 r
b111 7"
b101 v
b101 ."
1n
0g
b1 d
b1 z
b111 x
b111 :"
b11 #
b11 *
b11 -
b11 =
b11 e
b11 )"
b11 /"
b11 y
b11 ;"
b11 V"
b1100 f
b1100 P"
1$
#60
b1100 X
b1100 Y
b1100 Y"
0$
#65
0M"
0$"
0!"
1b
x5
1O
1P
bx X
14"
b111 Q
b111 {
b111 ^"
03
04
1;
b1 A
b1 D
b1 G
1L
b111 N
b111 0"
b111 \"
b0 V
b100 S
b100 ?"
b100 E"
b0 W
b0 X"
bx Y
bx Y"
b110 >
b110 B
b110 E
b110 I
b100001 H
b11 U
b11 ,"
b11 2"
b11 R"
b11 W"
b1100 R
b1100 |
b1100 *"
b110 M
b110 <"
b110 b"
b10 `
b10 1"
b10 >"
b0 a
b0 +"
b0 ="
b0 c
b0 }
b1 T
b1 @"
b1 ["
b1 Z"
b0 U"
b110 T"
b0 8"
b110 6"
b1 ?
b1 C
b100 @
b100 F
b11100 \
b11100 I"
b11100 L"
b100000000001000000000001100011 )
b100000000001000000000001100011 /
b100000000001000000000001100011 0
b100000000001000000000001100011 J
b100000000001000000000001100011 ~
b110 .
b111 y
b111 ;"
b111 V"
b11 f
b11 P"
b100 x
b100 :"
b101 !
b101 &
b101 ,
b101 2
b101 w
b111 #
b111 *
b111 -
b111 =
b111 e
b111 )"
b111 /"
b11000000101010 t
b11000000101010 ]"
b110 l
b110 a"
b100 s
b100 9"
b100 `"
b11 r
b11 7"
bx v
bx ."
b1100 u
b1100 ("
b111 d
b111 z
b11100 ]
b11100 F"
b11100 H"
b11000 [
b11000 '"
b11000 D"
b10000110000000000000000000001 :
b10000110000000000000000000001 _
b10000110000000000000000000001 #"
b11100 Z
b11100 %"
b11100 B"
b11100 G"
b11000 (
b11000 6
b11000 ^
b11000 C"
b11000 O"
1$
#70
0$
