SUPERSCALAR MIPS/mips_ss.sv
module top(input  logic clk, reset,
           output logic [31:0] writedata, dataadr,
           output logic memwrite);

  logic [31:0] pc;
  logic [63:0] instr;
  logic [31:0] readdata;

  mips_ss mips(clk, reset, pc, instr, memwrite, dataadr, writedata, readdata);
  imem imem(pc, instr);
  dmem dmem(clk, memwrite, dataadr, writedata, readdata);
endmodule

module mips_ss(input  logic clk, reset,
               output logic [31:0] pc,
               input  logic [63:0] instr,
               output logic memwrite,
               output logic [31:0] aluout, writedata,
               input  logic [31:0] readdata);

  logic [2:0] alucontrol_da, alucontrol_db;
  logic memtoreg_da, memwrite_da, alusrc_da, regdst_da, regwrite_da, jump_da, branch_da;
  logic memtoreg_db, memwrite_db, alusrc_db, regdst_db, regwrite_db, jump_db, branch_db;
  logic [31:0] instr_da, instr_db;
  logic issue_b;

  controller ca(instr_da[31:26], instr_da[5:0], memtoreg_da, memwrite_da, alusrc_da,
                regdst_da, regwrite_da, jump_da, branch_da, alucontrol_da);
  controller cb(instr_db[31:26], instr_db[5:0], memtoreg_db, memwrite_db, alusrc_db,
                regdst_db, regwrite_db, jump_db, branch_db, alucontrol_db);

  datapath_ss dp(clk, reset, memtoreg_da, memwrite_da, alusrc_da, regdst_da, regwrite_da, 
                 jump_da, branch_da, alucontrol_da, memtoreg_db, memwrite_db, alusrc_db, 
                 regdst_db, regwrite_db, jump_db, branch_db, alucontrol_db,
                 pc, instr, memwrite, aluout, writedata, readdata, instr_da, instr_db, issue_b);
endmodule

module controller(input  logic [5:0] op, funct,
                  output logic memtoreg, memwrite, alusrc,
                  output logic regdst, regwrite, jump, branch,
                  output logic [2:0] alucontrol);

  logic [1:0] aluop;
  maindec md(op, memtoreg, memwrite, branch, alusrc, regdst, regwrite, jump, aluop);
  aludec  ad(funct, aluop, alucontrol);
endmodule

module maindec(input  logic [5:0] op,
               output logic memtoreg, memwrite, branch, alusrc,
               output logic regdst, regwrite, jump,
               output logic [1:0] aluop);

  logic [8:0] controls;
  assign {regwrite, regdst, alusrc, branch, memwrite, memtoreg, jump, aluop} = controls;
  always_comb
    case(op)
      6'b000000: controls = 9'b1100000_10; 
      6'b100011: controls = 9'b1010010_00; 
      6'b101011: controls = 9'b0010100_00; 
      6'b000100: controls = 9'b0001000_01; 
      6'b001000: controls = 9'b1010000_00; 
      6'b000010: controls = 9'b0000001_00; 
      default:   controls = 9'b0000000_00;
    endcase
endmodule

module aludec(input  logic [5:0] funct,
              input  logic [1:0] aluop,
              output logic [2:0] alucontrol);

  always_comb
    case(aluop)
      2'b00: alucontrol = 3'b010; 
      2'b01: alucontrol = 3'b110; 
      default: case(funct)          
          6'b100000: alucontrol = 3'b010; 
          6'b100010: alucontrol = 3'b110; 
          6'b100100: alucontrol = 3'b000; 
          6'b100101: alucontrol = 3'b001; 
          6'b101010: alucontrol = 3'b111; 
          default:   alucontrol = 3'bxxx; 
        endcase
    endcase
endmodule

module datapath_ss(input  logic clk, reset,
                   input  logic memtoreg_da, memwrite_da, alusrc_da, regdst_da, regwrite_da, jump_da, branch_da,
                   input  logic [2:0] alucontrol_da,
                   input  logic memtoreg_db, memwrite_db, alusrc_db, regdst_db, regwrite_db, jump_db, branch_db,
                   input  logic [2:0] alucontrol_db,
                   output logic [31:0] pc_f,
                   input  logic [63:0] instr_f,
                   output logic memwrite_m,
                   output logic [31:0] aluout_m, writedata_m,
                   input  logic [31:0] readdata_m,
                   output logic [31:0] instr_da, instr_db,
                   output logic issue_b);

  logic [31:0] pcnext_f, pcplus4_f, pcplus8_f, pcbranch_d;
  logic [31:0] rd1a_d, rd2a_d, rd1b_d, rd2b_d;
  logic [31:0] signimma_d, signimmb_d;
  logic [31:0] aluouta_e, aluoutb_e, aluouta_m, aluoutb_m, result_wa, result_wb;
  logic [4:0]  wa3a, wa3b;
  logic        pcsrc_d, stall_f, stall_d, flush_e;

  hazard_ss h(instr_da[25:21], instr_da[20:16], instr_db[25:21], instr_db[20:16],
              regwrite_da, regwrite_db, memtoreg_da, memtoreg_db,
              wa3a, wa3b, issue_b, stall_f, stall_d, flush_e);

  assign pcsrc_d = branch_da & (rd1a_d == rd2a_d);
  assign pcplus4_f = pc_f + 4;
  assign pcplus8_f = pc_f + 8;
  assign pcnext_f = pcsrc_d ? pcbranch_d : (issue_b ? pcplus8_f : pcplus4_f);

  floprc #(32) pcreg(clk, reset, 1'b0, ~stall_f, pcnext_f, pc_f);
  
  floprc #(32) f_d_a(clk, reset, pcsrc_d, ~stall_d, instr_f[31:0], instr_da);
  floprc #(32) f_d_b(clk, reset, pcsrc_d | ~issue_b, ~stall_d, instr_f[63:32], instr_db);

  regfile_ss rf(clk, regwrite_wa, regwrite_wb, 
                instr_da[25:21], instr_da[20:16], instr_db[25:21], instr_db[20:16],
                wa3a_w, wa3b_w, result_wa, result_wb, 
                rd1a_d, rd2a_d, rd1b_d, rd2b_d);

  assign aluout_m = aluouta_m;
  assign result_wa = aluouta_m; 
  assign result_wb = aluoutb_m;

  alu alua(rd1a_d, rd2a_d, alucontrol_da, aluouta_e, zeroa);
  alu alub(rd1b_d, rd2b_d, alucontrol_db, aluoutb_e, zerob);

  always_ff @(posedge clk) begin
    aluouta_m <= aluouta_e;
    aluoutb_m <= aluoutb_e;
    regwrite_wa <= regwrite_da;
    regwrite_wb <= regwrite_db & issue_b;
    wa3a_w <= regdst_da ? instr_da[15:11] : instr_da[20:16];
    wa3b_w <= regdst_db ? instr_db[15:11] : instr_db[20:16];
  end

  logic regwrite_wa, regwrite_wb;
  logic [4:0] wa3a_w, wa3b_w;
  logic zeroa, zerob;
endmodule

module hazard_ss(input  logic [4:0] rs1a, rs2a, rs1b, rs2b,
                 input  logic regwrite_a, regwrite_b, memtoreg_a, memtoreg_b,
                 input  logic [4:0] wa3a, wa3b,
                 output logic issue_b, stall_f, stall_d, flush_e);

  always_comb begin
    issue_b = 1'b1;
    if (regwrite_a && (wa3a != 0)) begin
      if (wa3a == rs1b || wa3a == rs2b) issue_b = 1'b0;
    end
    if (memtoreg_a || memtoreg_b) issue_b = 1'b0;
  end

  assign stall_f = 1'b0;
  assign stall_d = 1'b0;
  assign flush_e = 1'b0;
endmodule

module regfile_ss(input  logic clk, we_a, we_b,
                  input  logic [4:0] ra1a, ra2a, ra1b, ra2b, wa_a, wa_b,
                  input  logic [31:0] wd_a, wd_b,
                  output logic [31:0] rd1a, rd2a, rd1b, rd2b);
  logic [31:0] rf[31:0];
  always_ff @(negedge clk) begin
    if (we_a) rf[wa_a] <= wd_a;
    if (we_b) rf[wa_b] <= wd_b;
  end
  assign rd1a = (ra1a != 0) ? rf[ra1a] : 0;
  assign rd2a = (ra2a != 0) ? rf[ra2a] : 0;
  assign rd1b = (ra1b != 0) ? rf[ra1b] : 0;
  assign rd2b = (ra2b != 0) ? rf[ra2b] : 0;
endmodule

module alu(input  logic [31:0] a, b, input  logic [2:0] alucontrol,
           output logic [31:0] result, output logic zero);
  always_comb
    case(alucontrol)
      3'b010: result = a + b;
      3'b110: result = a - b;
      3'b000: result = a & b;
      3'b001: result = a | b;
      3'b111: result = a < b ? 32'd1 : 32'd0;
      default: result = 32'bx;
    endcase
  assign zero = (result == 32'b0);
endmodule

module imem(input  logic [31:0] a, output logic [63:0] rd);
  logic [31:0] RAM[63:0];
  initial $readmemh("mips_ss_memfile.dat", RAM); 
  assign rd = {RAM[a[7:2] + 1], RAM[a[7:2]]};
endmodule

module dmem(input  logic clk, we, input  logic [31:0] a, wd, output logic [31:0] rd);
  logic [31:0] RAM[63:0];
  assign rd = RAM[a[31:2]];
  always_ff @(posedge clk) if (we) RAM[a[31:2]] <= wd;
endmodule

module floprc #(parameter WIDTH = 8)
                (input  logic clk, reset, clear, en, input  logic [WIDTH-1:0] d, output logic [WIDTH-1:0] q);
  always_ff @(posedge clk, posedge reset)
    if (reset)      q <= 0;
    else if (clear) q <= 0;
    else if (en)    q <= d;
endmodule

module mux2 #(parameter WIDTH = 8)
             (input  logic [WIDTH-1:0] d0, d1, input  logic s, output logic [WIDTH-1:0] y);
  assign y = s ? d1 : d0;
endmodule

SUPERSCALAR MIPS/mips_ss_tb.sv
module tb;
  logic clk;
  logic reset;
  logic [31:0] writedata, dataadr;
  logic memwrite;

  top dut(clk, reset, writedata, dataadr, memwrite);

  initial begin
    clk = 0;
    forever #5 clk = ~clk;
  end

  initial begin
    $dumpfile("dump.vcd");
    $dumpvars(0, tb);
    reset = 1;
    #12 reset = 0;
  end

  always @(negedge clk) begin
    if (memwrite) begin
      $display("Memory Write: Addr=%d, Data=%d", dataadr, writedata);
      if (dataadr === 84 && writedata === 7) begin
        $display("Simulation Succeeded!");
        $finish; 
      end 
    end
  end

  initial begin
    #1000; 
    $display("Simulation Timed Out.");
    $finish;
  end
endmodule

SUPERSCALAR MIPS/dump.vcd
$date
	Fri May 08 18:28:09 2026
$end
$version
	Icarus Verilog
$end
$timescale
	1s
$end
$scope module tb $end
$var wire 32 ! writedata [31:0] $end
$var wire 1 " memwrite $end
$var wire 32 # dataadr [31:0] $end
$var reg 1 $ clk $end
$var reg 1 % reset $end
$scope module dut $end
$var wire 1 $ clk $end
$var wire 1 % reset $end
$var wire 32 & writedata [31:0] $end
$var wire 32 ' readdata [31:0] $end
$var wire 32 ( pc [31:0] $end
$var wire 1 " memwrite $end
$var wire 64 ) instr [63:0] $end
$var wire 32 * dataadr [31:0] $end
$scope module dmem $end
$var wire 1 $ clk $end
$var wire 32 + rd [31:0] $end
$var wire 1 " we $end
$var wire 32 , wd [31:0] $end
$var wire 32 - a [31:0] $end
$upscope $end
$scope module imem $end
$var wire 64 . rd [63:0] $end
$var wire 32 / a [31:0] $end
$upscope $end
$scope module mips $end
$var wire 1 $ clk $end
$var wire 64 0 instr [63:0] $end
$var wire 32 1 readdata [31:0] $end
$var wire 1 % reset $end
$var wire 32 2 writedata [31:0] $end
$var wire 1 3 regwrite_db $end
$var wire 1 4 regwrite_da $end
$var wire 1 5 regdst_db $end
$var wire 1 6 regdst_da $end
$var wire 32 7 pc [31:0] $end
$var wire 1 8 memwrite_db $end
$var wire 1 9 memwrite_da $end
$var wire 1 " memwrite $end
$var wire 1 : memtoreg_db $end
$var wire 1 ; memtoreg_da $end
$var wire 1 < jump_db $end
$var wire 1 = jump_da $end
$var wire 1 > issue_b $end
$var wire 32 ? instr_db [31:0] $end
$var wire 32 @ instr_da [31:0] $end
$var wire 1 A branch_db $end
$var wire 1 B branch_da $end
$var wire 1 C alusrc_db $end
$var wire 1 D alusrc_da $end
$var wire 32 E aluout [31:0] $end
$var wire 3 F alucontrol_db [2:0] $end
$var wire 3 G alucontrol_da [2:0] $end
$scope module ca $end
$var wire 6 H funct [5:0] $end
$var wire 6 I op [5:0] $end
$var wire 1 4 regwrite $end
$var wire 1 6 regdst $end
$var wire 1 9 memwrite $end
$var wire 1 ; memtoreg $end
$var wire 1 = jump $end
$var wire 1 B branch $end
$var wire 1 D alusrc $end
$var wire 2 J aluop [1:0] $end
$var wire 3 K alucontrol [2:0] $end
$scope module ad $end
$var wire 6 L funct [5:0] $end
$var wire 2 M aluop [1:0] $end
$var reg 3 N alucontrol [2:0] $end
$upscope $end
$scope module md $end
$var wire 6 O op [5:0] $end
$var wire 1 4 regwrite $end
$var wire 1 6 regdst $end
$var wire 1 9 memwrite $end
$var wire 1 ; memtoreg $end
$var wire 1 = jump $end
$var wire 1 B branch $end
$var wire 1 D alusrc $end
$var wire 2 P aluop [1:0] $end
$var reg 9 Q controls [8:0] $end
$upscope $end
$upscope $end
$scope module cb $end
$var wire 6 R funct [5:0] $end
$var wire 6 S op [5:0] $end
$var wire 1 3 regwrite $end
$var wire 1 5 regdst $end
$var wire 1 8 memwrite $end
$var wire 1 : memtoreg $end
$var wire 1 < jump $end
$var wire 1 A branch $end
$var wire 1 C alusrc $end
$var wire 2 T aluop [1:0] $end
$var wire 3 U alucontrol [2:0] $end
$scope module ad $end
$var wire 6 V funct [5:0] $end
$var wire 2 W aluop [1:0] $end
$var reg 3 X alucontrol [2:0] $end
$upscope $end
$scope module md $end
$var wire 6 Y op [5:0] $end
$var wire 1 3 regwrite $end
$var wire 1 5 regdst $end
$var wire 1 8 memwrite $end
$var wire 1 : memtoreg $end
$var wire 1 < jump $end
$var wire 1 A branch $end
$var wire 1 C alusrc $end
$var wire 2 Z aluop [1:0] $end
$var reg 9 [ controls [8:0] $end
$upscope $end
$upscope $end
$scope module dp $end
$var wire 3 \ alucontrol_da [2:0] $end
$var wire 3 ] alucontrol_db [2:0] $end
$var wire 32 ^ aluout_m [31:0] $end
$var wire 1 D alusrc_da $end
$var wire 1 C alusrc_db $end
$var wire 1 B branch_da $end
$var wire 1 A branch_db $end
$var wire 1 $ clk $end
$var wire 1 _ flush_e $end
$var wire 64 ` instr_f [63:0] $end
$var wire 1 = jump_da $end
$var wire 1 < jump_db $end
$var wire 1 ; memtoreg_da $end
$var wire 1 : memtoreg_db $end
$var wire 1 9 memwrite_da $end
$var wire 1 8 memwrite_db $end
$var wire 1 a pcsrc_d $end
$var wire 32 b readdata_m [31:0] $end
$var wire 1 6 regdst_da $end
$var wire 1 5 regdst_db $end
$var wire 1 4 regwrite_da $end
$var wire 1 3 regwrite_db $end
$var wire 1 % reset $end
$var wire 32 c result_wa [31:0] $end
$var wire 32 d result_wb [31:0] $end
$var wire 1 e stall_d $end
$var wire 1 f stall_f $end
$var wire 1 g zerob $end
$var wire 1 h zeroa $end
$var wire 32 i rd2b_d [31:0] $end
$var wire 32 j rd2a_d [31:0] $end
$var wire 32 k rd1b_d [31:0] $end
$var wire 32 l rd1a_d [31:0] $end
$var wire 32 m pcplus8_f [31:0] $end
$var wire 32 n pcplus4_f [31:0] $end
$var wire 32 o pcnext_f [31:0] $end
$var wire 32 p pc_f [31:0] $end
$var wire 1 > issue_b $end
$var wire 32 q instr_db [31:0] $end
$var wire 32 r instr_da [31:0] $end
$var wire 32 s aluoutb_e [31:0] $end
$var wire 32 t aluouta_e [31:0] $end
$var reg 32 u aluouta_m [31:0] $end
$var reg 32 v aluoutb_m [31:0] $end
$var reg 1 " memwrite_m $end
$var reg 32 w pcbranch_d [31:0] $end
$var reg 1 x regwrite_wa $end
$var reg 1 y regwrite_wb $end
$var reg 5 z wa3a [4:0] $end
$var reg 5 { wa3a_w [4:0] $end
$var reg 5 | wa3b [4:0] $end
$var reg 5 } wa3b_w [4:0] $end
$var reg 32 ~ writedata_m [31:0] $end
$scope module alua $end
$var wire 3 !" alucontrol [2:0] $end
$var wire 1 h zero $end
$var wire 32 "" b [31:0] $end
$var wire 32 #" a [31:0] $end
$var reg 32 $" result [31:0] $end
$upscope $end
$scope module alub $end
$var wire 3 %" alucontrol [2:0] $end
$var wire 1 g zero $end
$var wire 32 &" b [31:0] $end
$var wire 32 '" a [31:0] $end
$var reg 32 (" result [31:0] $end
$upscope $end
$scope module f_d_a $end
$var wire 1 a clear $end
$var wire 1 $ clk $end
$var wire 32 )" d [31:0] $end
$var wire 1 *" en $end
$var wire 1 % reset $end
$var parameter 32 +" WIDTH $end
$var reg 32 ," q [31:0] $end
$upscope $end
$scope module f_d_b $end
$var wire 1 -" clear $end
$var wire 1 $ clk $end
$var wire 32 ." d [31:0] $end
$var wire 1 /" en $end
$var wire 1 % reset $end
$var parameter 32 0" WIDTH $end
$var reg 32 1" q [31:0] $end
$upscope $end
$scope module h $end
$var wire 1 _ flush_e $end
$var wire 1 ; memtoreg_a $end
$var wire 1 : memtoreg_b $end
$var wire 1 4 regwrite_a $end
$var wire 1 3 regwrite_b $end
$var wire 5 2" rs1a [4:0] $end
$var wire 5 3" rs1b [4:0] $end
$var wire 5 4" rs2a [4:0] $end
$var wire 5 5" rs2b [4:0] $end
$var wire 1 e stall_d $end
$var wire 1 f stall_f $end
$var wire 5 6" wa3a [4:0] $end
$var wire 5 7" wa3b [4:0] $end
$var reg 1 > issue_b $end
$upscope $end
$scope module pcreg $end
$var wire 1 8" clear $end
$var wire 1 $ clk $end
$var wire 32 9" d [31:0] $end
$var wire 1 :" en $end
$var wire 1 % reset $end
$var parameter 32 ;" WIDTH $end
$var reg 32 <" q [31:0] $end
$upscope $end
$scope module rf $end
$var wire 1 $ clk $end
$var wire 5 =" ra1a [4:0] $end
$var wire 5 >" ra1b [4:0] $end
$var wire 5 ?" ra2a [4:0] $end
$var wire 5 @" ra2b [4:0] $end
$var wire 5 A" wa_a [4:0] $end
$var wire 5 B" wa_b [4:0] $end
$var wire 32 C" wd_a [31:0] $end
$var wire 32 D" wd_b [31:0] $end
$var wire 1 x we_a $end
$var wire 1 y we_b $end
$var wire 32 E" rd2b [31:0] $end
$var wire 32 F" rd2a [31:0] $end
$var wire 32 G" rd1b [31:0] $end
$var wire 32 H" rd1a [31:0] $end
$upscope $end
$upscope $end
$upscope $end
$upscope $end
$upscope $end
$enddefinitions $end
$comment Show the parameter values. $end
$dumpall
b100000 ;"
b100000 0"
b100000 +"
$end
#0
$dumpvars
b0 H"
b0 G"
b0 F"
b0 E"
bx D"
bx C"
bx B"
bx A"
b0 @"
b0 ?"
b0 >"
b0 ="
b0 <"
1:"
b1000 9"
08"
bx 7"
bx 6"
b0 5"
b0 4"
b0 3"
b0 2"
b0 1"
1/"
b10000100001000100000100000 ."
0-"
b0 ,"
1*"
b100000000100000000000000000101 )"
bx ("
b0 '"
b0 &"
bx %"
bx $"
b0 #"
b0 ""
bx !"
bx ~
bx }
bx |
bx {
bx z
xy
xx
bx w
bx v
bx u
bx t
bx s
b0 r
b0 q
b0 p
b1000 o
b100 n
b1000 m
b0 l
b0 k
b0 j
b0 i
xh
xg
0f
0e
bx d
bx c
bx b
0a
b1000010000100010000010000000100000000100000000000000000101 `
0_
bx ^
bx ]
bx \
b110000010 [
b10 Z
b0 Y
bx X
b10 W
b0 V
bx U
b10 T
b0 S
b0 R
b110000010 Q
b10 P
b0 O
bx N
b10 M
b0 L
bx K
b10 J
b0 I
b0 H
bx G
bx F
bx E
0D
0C
0B
0A
b0 @
b0 ?
1>
0=
0<
0;
0:
09
08
b0 7
16
15
14
13
bx 2
bx 1
b1000010000100010000010000000100000000100000000000000000101 0
b0 /
b1000010000100010000010000000100000000100000000000000000101 .
bx -
bx ,
bx +
bx *
b1000010000100010000010000000100000000100000000000000000101 )
b0 (
bx '
bx &
1%
0$
bx #
x"
bx !
$end
#5
b0 }
b0 B"
b0 {
b0 A"
1y
1x
1$
#10
0$
#12
0%
#15
b10 G
b10 K
b10 N
b10 \
b10 !"
06
1D
b0 J
b0 M
b0 P
b10000 o
b10000 9"
b10001100011001000000100000 )"
b10101100000100100000000001010100 ."
bx j
bx ""
bx F"
b101000000 Q
bx i
bx &"
bx E"
bx k
bx '"
bx G"
b10 F
b10 U
b10 X
b10 ]
b10 %"
b1010110000010010000000000101010000000010001100011001000000100000 )
b1010110000010010000000000101010000000010001100011001000000100000 .
b1010110000010010000000000101010000000010001100011001000000100000 0
b1010110000010010000000000101010000000010001100011001000000100000 `
b10000 ?"
b10000 4"
b101 H
b101 L
b1000 I
b1000 O
b10000 @"
b10000 >"
b10000 5"
b10000 3"
b100000 R
b100000 V
b10000 m
b1100 n
b1000 (
b1000 /
b1000 7
b1000 p
b1000 <"
b100000000100000000000000000101 @
b100000000100000000000000000101 r
b100000000100000000000000000101 ,"
b10000100001000100000100000 ?
b10000100001000100000100000 q
b10000100001000100000100000 1"
1$
#20
0$
#25
03
05
1C
18
b0 T
b0 W
b0 Z
16
0D
b10 J
b10 M
b10 P
b0 k
b0 '"
b0 G"
b10 F
b10 U
b10 X
b10 ]
b10 %"
b1010000 [
bx l
bx #"
bx H"
b110000010 Q
b11000 o
b11000 9"
bx )"
bx ."
b10010 @"
b0 >"
b10010 5"
b0 3"
b10100 R
b10100 V
b101011 S
b101011 Y
b10001 ?"
b10001 ="
b10001 4"
b10001 2"
b100000 H
b100000 L
b0 I
b0 O
bx )
bx .
bx 0
bx `
b10001 }
b10001 B"
b10000 {
b10000 A"
b10101100000100100000000001010100 ?
b10101100000100100000000001010100 q
b10101100000100100000000001010100 1"
b10001100011001000000100000 @
b10001100011001000000100000 r
b10001100011001000000100000 ,"
b11000 m
b10100 n
b10000 (
b10000 /
b10000 7
b10000 p
b10000 <"
1$
#30
0$
#35
04
06
b0 J
b0 M
b0 P
0C
08
b100000 o
b100000 9"
b10 G
b10 K
b10 N
b10 \
b10 !"
b0 Q
bx k
bx '"
bx G"
b0 [
bx ?"
bx ="
bx 4"
bx 2"
bx H
bx L
bx I
bx O
bx @"
bx >"
bx 5"
bx 3"
bx R
bx V
bx S
bx Y
b10010 }
b10010 B"
b10010 {
b10010 A"
0y
b100000 m
b11100 n
b11000 (
b11000 /
b11000 7
b11000 p
b11000 <"
bx @
bx r
bx ,"
bx ?
bx q
bx 1"
1$
#40
0$
#45
b101000 o
b101000 9"
bx }
bx B"
bx {
bx A"
0x
b101000 m
b100100 n
b100000 (
b100000 /
b100000 7
b100000 p
b100000 <"
1$
#50
0$
#55
b110000 o
b110000 9"
b110000 m
b101100 n
b101000 (
b101000 /
b101000 7
b101000 p
b101000 <"
1$
#60
0$
#65
b111000 o
b111000 9"
b111000 m
b110100 n
b110000 (
b110000 /
b110000 7
b110000 p
b110000 <"
1$
#70
0$
#75
b1000000 o
b1000000 9"
b1000000 m
b111100 n
b111000 (
b111000 /
b111000 7
b111000 p
b111000 <"
1$
#80
0$
#85
b1001000 o
b1001000 9"
b1001000 m
b1000100 n
b1000000 (
b1000000 /
b1000000 7
b1000000 p
b1000000 <"
1$
#90
0$
#95
b1010000 o
b1010000 9"
b1010000 m
b1001100 n
b1001000 (
b1001000 /
b1001000 7
b1001000 p
b1001000 <"
1$
#100
0$
#105
b1011000 o
b1011000 9"
b1011000 m
b1010100 n
b1010000 (
b1010000 /
b1010000 7
b1010000 p
b1010000 <"
1$
#110
0$
#115
b1100000 o
b1100000 9"
b1100000 m
b1011100 n
b1011000 (
b1011000 /
b1011000 7
b1011000 p
b1011000 <"
1$
#120
0$
#125
b1101000 o
b1101000 9"
b1101000 m
b1100100 n
b1100000 (
b1100000 /
b1100000 7
b1100000 p
b1100000 <"
1$
#130
0$
#135
b1110000 o
b1110000 9"
b1110000 m
b1101100 n
b1101000 (
b1101000 /
b1101000 7
b1101000 p
b1101000 <"
1$
#140
0$
#145
b1111000 o
b1111000 9"
b1111000 m
b1110100 n
b1110000 (
b1110000 /
b1110000 7
b1110000 p
b1110000 <"
1$
#150
0$
#155
b10000000 o
b10000000 9"
b10000000 m
b1111100 n
b1111000 (
b1111000 /
b1111000 7
b1111000 p
b1111000 <"
1$
#160
0$
#165
b10001000 o
b10001000 9"
b10001000 m
b10000100 n
b10000000 (
b10000000 /
b10000000 7
b10000000 p
b10000000 <"
1$
#170
0$
#175
b10010000 o
b10010000 9"
b10010000 m
b10001100 n
b10001000 (
b10001000 /
b10001000 7
b10001000 p
b10001000 <"
1$
#180
0$
#185
b10011000 o
b10011000 9"
b10011000 m
b10010100 n
b10010000 (
b10010000 /
b10010000 7
b10010000 p
b10010000 <"
1$
#190
0$
#195
b10100000 o
b10100000 9"
b10100000 m
b10011100 n
b10011000 (
b10011000 /
b10011000 7
b10011000 p
b10011000 <"
1$
#200
0$
#205
b10101000 o
b10101000 9"
b10101000 m
b10100100 n
b10100000 (
b10100000 /
b10100000 7
b10100000 p
b10100000 <"
1$
#210
0$
#215
b10110000 o
b10110000 9"
b10110000 m
b10101100 n
b10101000 (
b10101000 /
b10101000 7
b10101000 p
b10101000 <"
1$
#220
0$
#225
b10111000 o
b10111000 9"
b10111000 m
b10110100 n
b10110000 (
b10110000 /
b10110000 7
b10110000 p
b10110000 <"
1$
#230
0$
#235
b11000000 o
b11000000 9"
b11000000 m
b10111100 n
b10111000 (
b10111000 /
b10111000 7
b10111000 p
b10111000 <"
1$
#240
0$
#245
b11001000 o
b11001000 9"
b11001000 m
b11000100 n
b11000000 (
b11000000 /
b11000000 7
b11000000 p
b11000000 <"
1$
#250
0$
#255
b11010000 o
b11010000 9"
b11010000 m
b11001100 n
b11001000 (
b11001000 /
b11001000 7
b11001000 p
b11001000 <"
1$
#260
0$
#265
b11011000 o
b11011000 9"
b11011000 m
b11010100 n
b11010000 (
b11010000 /
b11010000 7
b11010000 p
b11010000 <"
1$
#270
0$
#275
b11100000 o
b11100000 9"
b11100000 m
b11011100 n
b11011000 (
b11011000 /
b11011000 7
b11011000 p
b11011000 <"
1$
#280
0$
#285
b11101000 o
b11101000 9"
b11101000 m
b11100100 n
b11100000 (
b11100000 /
b11100000 7
b11100000 p
b11100000 <"
1$
#290
0$
#295
b11110000 o
b11110000 9"
b11110000 m
b11101100 n
b11101000 (
b11101000 /
b11101000 7
b11101000 p
b11101000 <"
1$
#300
0$
#305
b11111000 o
b11111000 9"
b11111000 m
b11110100 n
b11110000 (
b11110000 /
b11110000 7
b11110000 p
b11110000 <"
1$
#310
0$
#315
b100000000 o
b100000000 9"
b100000000 m
b11111100 n
b11111000 (
b11111000 /
b11111000 7
b11111000 p
b11111000 <"
1$
#320
0$
#325
b100001000 o
b100001000 9"
b100000000100000000000000000101 )"
b10000100001000100000100000 ."
b1000010000100010000010000000100000000100000000000000000101 )
b1000010000100010000010000000100000000100000000000000000101 .
b1000010000100010000010000000100000000100000000000000000101 0
b1000010000100010000010000000100000000100000000000000000101 `
b100001000 m
b100000100 n
b100000000 (
b100000000 /
b100000000 7
b100000000 p
b100000000 <"
1$
#330
0$
#335
14
1D
13
15
b10 T
b10 W
b10 Z
b100010000 o
b100010000 9"
b10001100011001000000100000 )"
b10101100000100100000000001010100 ."
b0 l
b0 #"
b0 H"
b101000000 Q
b110000010 [
b1010110000010010000000000101010000000010001100011001000000100000 )
b1010110000010010000000000101010000000010001100011001000000100000 .
b1010110000010010000000000101010000000010001100011001000000100000 0
b1010110000010010000000000101010000000010001100011001000000100000 `
b10000 ?"
b0 ="
b10000 4"
b0 2"
b101 H
b101 L
b1000 I
b1000 O
b10000 @"
b10000 >"
b10000 5"
b10000 3"
b100000 R
b100000 V
b0 S
b0 Y
b100010000 m
b100001100 n
b100001000 (
b100001000 /
b100001000 7
b100001000 p
b100001000 <"
b100000000100000000000000000101 @
b100000000100000000000000000101 r
b100000000100000000000000000101 ,"
b10000100001000100000100000 ?
b10000100001000100000100000 q
b10000100001000100000100000 1"
1$
#340
0$
#345
03
05
1C
18
b0 T
b0 W
b0 Z
16
0D
b10 J
b10 M
b10 P
b0 k
b0 '"
b0 G"
b10 F
b10 U
b10 X
b10 ]
b10 %"
b1010000 [
bx l
bx #"
bx H"
b110000010 Q
b100011000 o
b100011000 9"
bx )"
bx ."
b10010 @"
b0 >"
b10010 5"
b0 3"
b10100 R
b10100 V
b101011 S
b101011 Y
b10001 ?"
b10001 ="
b10001 4"
b10001 2"
b100000 H
b100000 L
b0 I
b0 O
bx )
bx .
bx 0
bx `
b10001 }
b10001 B"
b10000 {
b10000 A"
1y
1x
b10101100000100100000000001010100 ?
b10101100000100100000000001010100 q
b10101100000100100000000001010100 1"
b10001100011001000000100000 @
b10001100011001000000100000 r
b10001100011001000000100000 ,"
b100011000 m
b100010100 n
b100010000 (
b100010000 /
b100010000 7
b100010000 p
b100010000 <"
1$
#350
0$
#355
04
06
b0 J
b0 M
b0 P
0C
08
b100100000 o
b100100000 9"
b10 G
b10 K
b10 N
b10 \
b10 !"
b0 Q
bx k
bx '"
bx G"
b0 [
bx ?"
bx ="
bx 4"
bx 2"
bx H
bx L
bx I
bx O
bx @"
bx >"
bx 5"
bx 3"
bx R
bx V
bx S
bx Y
b10010 }
b10010 B"
b10010 {
b10010 A"
0y
b100100000 m
b100011100 n
b100011000 (
b100011000 /
b100011000 7
b100011000 p
b100011000 <"
bx @
bx r
bx ,"
bx ?
bx q
bx 1"
1$
#360
0$
#365
b100101000 o
b100101000 9"
bx }
bx B"
bx {
bx A"
0x
b100101000 m
b100100100 n
b100100000 (
b100100000 /
b100100000 7
b100100000 p
b100100000 <"
1$
#370
0$
#375
b100110000 o
b100110000 9"
b100110000 m
b100101100 n
b100101000 (
b100101000 /
b100101000 7
b100101000 p
b100101000 <"
1$
#380
0$
#385
b100111000 o
b100111000 9"
b100111000 m
b100110100 n
b100110000 (
b100110000 /
b100110000 7
b100110000 p
b100110000 <"
1$
#390
0$
#395
b101000000 o
b101000000 9"
b101000000 m
b100111100 n
b100111000 (
b100111000 /
b100111000 7
b100111000 p
b100111000 <"
1$
#400
0$
#405
b101001000 o
b101001000 9"
b101001000 m
b101000100 n
b101000000 (
b101000000 /
b101000000 7
b101000000 p
b101000000 <"
1$
#410
0$
#415
b101010000 o
b101010000 9"
b101010000 m
b101001100 n
b101001000 (
b101001000 /
b101001000 7
b101001000 p
b101001000 <"
1$
#420
0$
#425
b101011000 o
b101011000 9"
b101011000 m
b101010100 n
b101010000 (
b101010000 /
b101010000 7
b101010000 p
b101010000 <"
1$
#430
0$
#435
b101100000 o
b101100000 9"
b101100000 m
b101011100 n
b101011000 (
b101011000 /
b101011000 7
b101011000 p
b101011000 <"
1$
#440
0$
#445
b101101000 o
b101101000 9"
b101101000 m
b101100100 n
b101100000 (
b101100000 /
b101100000 7
b101100000 p
b101100000 <"
1$
#450
0$
#455
b101110000 o
b101110000 9"
b101110000 m
b101101100 n
b101101000 (
b101101000 /
b101101000 7
b101101000 p
b101101000 <"
1$
#460
0$
#465
b101111000 o
b101111000 9"
b101111000 m
b101110100 n
b101110000 (
b101110000 /
b101110000 7
b101110000 p
b101110000 <"
1$
#470
0$
#475
b110000000 o
b110000000 9"
b110000000 m
b101111100 n
b101111000 (
b101111000 /
b101111000 7
b101111000 p
b101111000 <"
1$
#480
0$
